skir/__init__.py
skir/_module_initializer.py
skir/_spec.py
skir/reflection.py
skir/_impl/__init__.py
skir/_impl/arrays.py
skir/_impl/binary.py
skir/_impl/enums.py
skir/_impl/function_maker.py
skir/_impl/keep.py
skir/_impl/keyed_items.py
skir/_impl/method.py
skir/_impl/never.py
skir/_impl/optionals.py
skir/_impl/primitives.py
skir/_impl/repr.py
skir/_impl/serializer.py
skir/_impl/serializers.py
skir/_impl/service.py
skir/_impl/service_client.py
skir/_impl/structs.py
skir/_impl/timestamp.py
skir/_impl/type_adapter.py
skir_client-1.0.5.dist-info/licenses/LICENSE
skir_client-1.0.5.dist-info/METADATA
skir_client-1.0.5.dist-info/WHEEL
skir_client-1.0.5.dist-info/top_level.txt
skir_client-1.0.5.dist-info/RECORD
