Metadata-Version: 2.4
Name: skir-client
Version: 1.0.5
Author-email: Tyler Fibonacci <gepheum@gmail.com>
License: MIT License
Project-URL: Homepage, https://github.com/gepheum/skir-python-client
Classifier: License :: OSI Approved :: MIT License
Classifier: Programming Language :: Python
Classifier: Programming Language :: Python :: 3
Requires-Python: >=3.10
License-File: LICENSE
Dynamic: license-file
